mugeshcalcu/__init__.py
mugeshcalcu/calculator.py
mugeshcalcu-1.0.0.dist-info/licenses/LICENSE
mugeshcalcu-1.0.0.dist-info/METADATA
mugeshcalcu-1.0.0.dist-info/WHEEL
mugeshcalcu-1.0.0.dist-info/top_level.txt
mugeshcalcu-1.0.0.dist-info/RECORD
