Metadata-Version: 2.4
Name: mugeshcalcu
Version: 1.0.0
Summary: Simple calculator library for addition and multiplication by Mugesh
Author: Mugesh
License: MIT
Requires-Python: >=3.7
License-File: LICENSE
Dynamic: author
Dynamic: license
Dynamic: license-file
Dynamic: requires-python
Dynamic: summary
